cnes_checker/__init__.py
cnes_checker/cnes_checker.py
cnes_pylint_extension-7.0.0.dist-info/LICENSE
cnes_pylint_extension-7.0.0.dist-info/METADATA
cnes_pylint_extension-7.0.0.dist-info/WHEEL
cnes_pylint_extension-7.0.0.dist-info/top_level.txt
cnes_pylint_extension-7.0.0.dist-info/RECORD
