Metadata-Version: 2.1
Name: cnes-pylint-extension
Version: 7.0.0
Summary: A PyLint plugin to add CNES specific checks
Home-page: https://github.com/cnescatlab/cnes-pylint-extension
Author: CNES CatLab
Project-URL: Bug Reports, https://github.com/cnescatlab/cnes-pylint-extension/issues
Classifier: Programming Language :: Python :: 3
Classifier: License :: OSI Approved :: GNU General Public License v3 (GPLv3)
Classifier: Operating System :: OS Independent
Requires-Python: >=3.8
License-File: LICENSE
Requires-Dist: pylint-plugin-utils ==0.7
Requires-Dist: pylint <4.0.0,>=3.0.0
